elabftwcontrol/__init__.py
elabftwcontrol/_logging.py
elabftwcontrol/cli.py
elabftwcontrol/client.py
elabftwcontrol/configure.py
elabftwcontrol/defaults.py
elabftwcontrol/global_config.py
elabftwcontrol/py.typed
elabftwcontrol/s3_utils.py
elabftwcontrol/testing_utils.py
elabftwcontrol/types.py
elabftwcontrol/utils.py
elabftwcontrol/core/__init__.py
elabftwcontrol/core/interfaces.py
elabftwcontrol/core/manifests.py
elabftwcontrol/core/metadata.py
elabftwcontrol/core/models.py
elabftwcontrol/core/parsers.py
elabftwcontrol/core/transformers.py
elabftwcontrol/download/__init__.py
elabftwcontrol/download/api.py
elabftwcontrol/download/output.py
elabftwcontrol/upload/__init__.py
elabftwcontrol/upload/api.py
elabftwcontrol/upload/diff.py
elabftwcontrol/upload/graph.py
elabftwcontrol/upload/jobs.py
elabftwcontrol/upload/parsers.py
elabftwcontrol/upload/state.py
elabftwcontrol-0.2.4.dist-info/licenses/LICENSE
elabftwcontrol-0.2.4.dist-info/METADATA
elabftwcontrol-0.2.4.dist-info/WHEEL
elabftwcontrol-0.2.4.dist-info/entry_points.txt
elabftwcontrol-0.2.4.dist-info/top_level.txt
elabftwcontrol-0.2.4.dist-info/RECORD
