Metadata-Version: 2.4
Name: elabftwcontrol
Version: 0.2.4
Summary: Package for easily interacting with eLabFTW data from the cli and in Python
Author-email: Niels Cautaerts <niels.cautaerts@vito.be>
Project-URL: Repository, https://github.com/din14970/elabftwcontrol
Keywords: science,lab notebooks,data management
Classifier: Topic :: Scientific/Engineering
Classifier: Programming Language :: Python :: Implementation :: CPython
Classifier: Programming Language :: Python :: 3.10
Classifier: Programming Language :: Python :: 3.11
Classifier: Programming Language :: Python :: 3.12
Requires-Python: >=3.10
License-File: LICENSE
Requires-Dist: elabapi-python~=5.0
Requires-Dist: pydantic~=2.4
Requires-Dist: pandas~=2.0
Requires-Dist: typer~=0.15
Requires-Dist: tabulate~=0.9
Requires-Dist: pyyaml~=6.0
Requires-Dist: gitpython~=3.1
Provides-Extra: excel
Requires-Dist: openpyxl~=3.1; extra == "excel"
Requires-Dist: xlsxwriter~=3.2; extra == "excel"
Provides-Extra: aws
Requires-Dist: awswrangler~=3.7; extra == "aws"
Requires-Dist: s3fs>=2024.3; extra == "aws"
Dynamic: license-file
